LICENSE
MANIFEST.in
README.md
requirements-dev.txt
requirements.txt
setup.py
ibm_cloud_databases/__init__.py
ibm_cloud_databases/cloud_databases_v5.py
ibm_cloud_databases/common.py
ibm_cloud_databases/version.py
ibm_cloud_databases.egg-info/PKG-INFO
ibm_cloud_databases.egg-info/SOURCES.txt
ibm_cloud_databases.egg-info/dependency_links.txt
ibm_cloud_databases.egg-info/requires.txt
ibm_cloud_databases.egg-info/top_level.txt
ibm_cloud_databases.egg-info/zip-safe