Metadata-Version: 2.1
Name: ibm-cloud-databases
Version: 0.1.0
Summary: Python client library for IBM Cloud Databases service
Home-page: https://github.com/IBM/cloud-databases-python-sdk
Author: IBM
Author-email: devexdev@us.ibm.com
License: Apache 2.0
Keywords: ibm_cloud_databases
Platform: UNKNOWN
Classifier: Programming Language :: Python
Classifier: Programming Language :: Python :: 3
Classifier: Programming Language :: Python :: 3.6
Classifier: Programming Language :: Python :: 3.7
Classifier: Programming Language :: Python :: 3.8
Classifier: Programming Language :: Python :: 3.9
Classifier: Development Status :: 4 - Beta
Classifier: Intended Audience :: Developers
Classifier: License :: OSI Approved :: Apache Software License
Classifier: Operating System :: OS Independent
Classifier: Topic :: Software Development :: Libraries :: Python Modules
Classifier: Topic :: Software Development :: Libraries :: Application Frameworks
